{
  "buffer_name": "game.lua",
  "entries": [
    {
      "patch_source": {
        "file": "DVPreview_v4.1.2\\lovely\\settings.toml",
        "patch_type": "copy"
      },
      "regions": [
        {
          "start_line": 3762,
          "end_line": 3857
        }
      ]
    },
    {
      "patch_source": {
        "file": "smods-1.0.0-beta-1224a\\lovely\\back.toml",
        "pattern": "self.GAME.selected_back = Back(selected_back)",
        "patch_type": "pattern"
      },
      "regions": [
        {
          "start_line": 2075,
          "end_line": 2077
        }
      ]
    },
    {
      "patch_source": {
        "file": "smods-1.0.0-beta-1224a\\lovely\\better_calc.toml",
        "pattern": "if G.GAME.current_round.hands_played == 0 and\n    G.GAME.current_round.discards_used == 0 and G.GAME.facing_blind then\n    for i = 1, #G.jokers.cards do\n        G.jokers.cards[i]:calculate_joker({first_hand_drawn = true})\n    end\nend\n",
        "patch_type": "pattern"
      },
      "regions": [
        {
          "start_line": 3359,
          "end_line": 3359
        }
      ]
    },
    {
      "patch_source": {
        "file": "smods-1.0.0-beta-1224a\\lovely\\better_calc.toml",
        "pattern": "G.CONTROLLER:snap_to({node = G.shop:get_UIE_by_ID('next_round_button')})\n",
        "patch_type": "pattern"
      },
      "regions": [
        {
          "start_line": 3286,
          "end_line": 3286
        }
      ]
    },
    {
      "patch_source": {
        "file": "smods-1.0.0-beta-1224a\\lovely\\better_calc.toml",
        "pattern": "self.deck = CardArea(",
        "patch_type": "pattern"
      },
      "regions": [
        {
          "start_line": 2319,
          "end_line": 2323
        }
      ]
    },
    {
      "patch_source": {
        "file": "smods-1.0.0-beta-1224a\\lovely\\better_calc.toml",
        "pattern": "{n=G.UIT.O, config={object = DynaText({scale = 0.6, string = G.GAME.blind:get_loc_debuff_text(), maxw = 9, colours = {G.C.WHITE},float = true, shadow = true, silent = true, pop_in = 0, pop_in_rate = 6})}},",
        "patch_type": "pattern"
      },
      "regions": [
        {
          "start_line": 2623,
          "end_line": 2623
        }
      ]
    },
    {
      "patch_source": {
        "file": "smods-1.0.0-beta-1224a\\lovely\\blind_ui.toml",
        "pattern": "config = {major = G.HUD:get_UIE_by_ID('row_blind'), align = 'cm', offset = {x=0,y=-10}, bond = 'Weak'}",
        "patch_type": "pattern"
      },
      "regions": [
        {
          "start_line": 2492,
          "end_line": 2492
        }
      ]
    },
    {
      "patch_source": {
        "file": "smods-1.0.0-beta-1224a\\lovely\\blind_ui.toml",
        "pattern": "G.GAME.blind.children.animatedSprite:juice_up(0.05, 0.02)",
        "patch_type": "pattern"
      },
      "regions": [
        {
          "start_line": 2634,
          "end_line": 2638
        }
      ]
    },
    {
      "patch_source": {
        "file": "smods-1.0.0-beta-1224a\\lovely\\card_limit.toml",
        "pattern": "local saveTable = args.savetext or nil\n",
        "patch_type": "pattern"
      },
      "regions": [
        {
          "start_line": 2049,
          "end_line": 2049
        }
      ]
    },
    {
      "patch_source": {
        "file": "smods-1.0.0-beta-1224a\\lovely\\card_limit.toml",
        "pattern": "{card_limit = self.GAME.starting_params.consumable_slots, type = 'joker', highlight_limit = 1})\n",
        "patch_type": "pattern"
      },
      "regions": [
        {
          "start_line": 2307,
          "end_line": 2307
        }
      ]
    },
    {
      "patch_source": {
        "file": "smods-1.0.0-beta-1224a\\lovely\\card_limit.toml",
        "pattern": "{card_limit = self.GAME.starting_params.joker_slots, type = 'joker', highlight_limit = 1})\n",
        "patch_type": "pattern"
      },
      "regions": [
        {
          "start_line": 2313,
          "end_line": 2313
        }
      ]
    },
    {
      "patch_source": {
        "file": "smods-1.0.0-beta-1224a\\lovely\\card_limit.toml",
        "pattern": "{card_limit = self.GAME.starting_params.hand_size, type = 'hand'})\n",
        "patch_type": "pattern"
      },
      "regions": [
        {
          "start_line": 2331,
          "end_line": 2331
        }
      ]
    },
    {
      "patch_source": {
        "file": "smods-1.0.0-beta-1224a\\lovely\\card_limit.toml",
        "pattern": "{card_limit = 5, type = 'play'})\n",
        "patch_type": "pattern"
      },
      "regions": [
        {
          "start_line": 2335,
          "end_line": 2335
        }
      ]
    },
    {
      "patch_source": {
        "file": "smods-1.0.0-beta-1224a\\lovely\\cardareas.toml",
        "pattern": "G.playing_cards = {}\n\nset_screen_positions()\n",
        "patch_type": "pattern"
      },
      "regions": [
        {
          "start_line": 2340,
          "end_line": 2344
        }
      ]
    },
    {
      "patch_source": {
        "file": "smods-1.0.0-beta-1224a\\lovely\\crash_handler.toml",
        "pattern": "local saveTable = args.savetext or nil\n",
        "patch_type": "pattern"
      },
      "regions": [
        {
          "start_line": 2048,
          "end_line": 2048
        }
      ]
    },
    {
      "patch_source": {
        "file": "smods-1.0.0-beta-1224a\\lovely\\edition.toml",
        "pattern": "table.sort(self.P_CENTER_POOLS[\"Enhanced\"], function (a, b) return a.order < b.order end)",
        "patch_type": "pattern"
      },
      "regions": [
        {
          "start_line": 856,
          "end_line": 856
        }
      ]
    },
    {
      "patch_source": {
        "file": "smods-1.0.0-beta-1224a\\lovely\\enhancement.toml",
        "pattern": "modulate_sound(dt)",
        "patch_type": "pattern"
      },
      "regions": [
        {
          "start_line": 2550,
          "end_line": 2550
        }
      ]
    },
    {
      "patch_source": {
        "file": "smods-1.0.0-beta-1224a\\lovely\\fixes.toml",
        "pattern": "function Game:delete_run()",
        "patch_type": "pattern"
      },
      "regions": [
        {
          "start_line": 1169,
          "end_line": 1170
        }
      ]
    },
    {
      "patch_source": {
        "file": "smods-1.0.0-beta-1224a\\lovely\\fixes.toml",
        "pattern": "G.STATE = -1",
        "patch_type": "pattern"
      },
      "regions": [
        {
          "start_line": 1217,
          "end_line": 1217
        }
      ]
    },
    {
      "patch_source": {
        "file": "smods-1.0.0-beta-1224a\\lovely\\gradient.toml",
        "pattern": "self.C.EDITION[2] = 0.7+0.2*(1+math.sin(self.TIMERS.REAL*1.5 + 6))",
        "patch_type": "pattern"
      },
      "regions": [
        {
          "start_line": 2605,
          "end_line": 2607
        }
      ]
    },
    {
      "patch_source": {
        "file": "smods-1.0.0-beta-1224a\\lovely\\hand_limit.toml",
        "pattern": "self.GAME = saveTable and saveTable.GAME or self:init_game_object()\n",
        "patch_type": "pattern"
      },
      "regions": [
        {
          "start_line": 2070,
          "end_line": 2070
        }
      ]
    },
    {
      "patch_source": {
        "file": "smods-1.0.0-beta-1224a\\lovely\\jimboquip.toml",
        "pattern": "Jimbo = Card_Character({x = 0, y = 5})\nlocal spot = G.OVERLAY_MENU:get_UIE_by_ID('jimbo_spot')\nspot.config.object:remove()\nspot.config.object = Jimbo\nJimbo.ui_object_updated = true\nJimbo:add_speech_bubble('lq_'..math.random(1,10), nil, {quip = true})\nJimbo:say_stuff(5)\n",
        "patch_type": "pattern"
      },
      "regions": [
        {
          "start_line": 3740,
          "end_line": 3749
        }
      ]
    },
    {
      "patch_source": {
        "file": "smods-1.0.0-beta-1224a\\lovely\\language.toml",
        "pattern": "if not (love.filesystem.read('localization/'..G.SETTINGS.language..'.lua')) or G.F_ENGLISH_ONLY then",
        "patch_type": "pattern"
      },
      "regions": [
        {
          "start_line": 950,
          "end_line": 950
        }
      ]
    },
    {
      "patch_source": {
        "file": "smods-1.0.0-beta-1224a\\lovely\\language.toml",
        "pattern": "local localization = love.filesystem.getInfo('localization/'..G.SETTINGS.language..'.lua')",
        "patch_type": "pattern"
      },
      "regions": [
        {
          "start_line": 1012,
          "end_line": 1012
        }
      ]
    },
    {
      "patch_source": {
        "file": "smods-1.0.0-beta-1224a\\lovely\\language.toml",
        "pattern": "self.localization = assert(loadstring(love.filesystem.read('localization/'..G.SETTINGS.language..'.lua')))()",
        "patch_type": "pattern"
      },
      "regions": [
        {
          "start_line": 1014,
          "end_line": 1014
        }
      ]
    },
    {
      "patch_source": {
        "file": "smods-1.0.0-beta-1224a\\lovely\\language.toml",
        "pattern": "self.LANG = self.LANGUAGES[self.SETTINGS.language] or self.LANGUAGES['en-us']",
        "patch_type": "pattern"
      },
      "regions": [
        {
          "start_line": 1010,
          "end_line": 1010
        }
      ]
    },
    {
      "patch_source": {
        "file": "smods-1.0.0-beta-1224a\\lovely\\playing_card.toml",
        "pattern": "function Game:init_game_object()",
        "patch_type": "pattern"
      },
      "regions": [
        {
          "start_line": 1895,
          "end_line": 1898
        }
      ]
    },
    {
      "patch_source": {
        "file": "smods-1.0.0-beta-1224a\\lovely\\playing_card.toml",
        "pattern": "local _ = nil",
        "patch_type": "pattern"
      },
      "regions": [
        {
          "start_line": 2419,
          "end_line": 2422
        }
      ]
    },
    {
      "patch_source": {
        "file": "smods-1.0.0-beta-1224a\\lovely\\playing_card.toml",
        "pattern": "if self.GAME.starting_params.erratic_suits_and_ranks then _, k = pseudorandom_element(G.P_CARDS, pseudoseed('erratic')) end",
        "patch_type": "pattern"
      },
      "regions": [
        {
          "start_line": 2424,
          "end_line": 2426
        }
      ]
    },
    {
      "patch_source": {
        "file": "smods-1.0.0-beta-1224a\\lovely\\playing_card.toml",
        "pattern": "local _r, _s = string.sub(k, 3, 3), string.sub(k, 1, 1)",
        "patch_type": "pattern"
      },
      "regions": [
        {
          "start_line": 2427,
          "end_line": 2427
        }
      ]
    },
    {
      "patch_source": {
        "file": "smods-1.0.0-beta-1224a\\lovely\\playing_card.toml",
        "pattern": "if self.GAME.starting_params.no_faces and (_r == 'K' or _r == 'Q' or _r == 'J') then keep = false end",
        "patch_type": "pattern"
      },
      "regions": [
        {
          "start_line": 2439,
          "end_line": 2439
        }
      ]
    },
    {
      "patch_source": {
        "file": "smods-1.0.0-beta-1224a\\lovely\\playing_card.toml",
        "pattern": "if keep then card_protos[#card_protos+1] = {s=_s,r=_r,e=_e,d=_d,g=_g} end",
        "patch_type": "pattern"
      },
      "regions": [
        {
          "start_line": 2442,
          "end_line": 2442
        }
      ]
    },
    {
      "patch_source": {
        "file": "smods-1.0.0-beta-1224a\\lovely\\rarity.toml",
        "pattern": "self.C.EDITION[2] = 0.7+0.2*(1+math.sin(self.TIMERS.REAL*1.5 + 6))",
        "patch_type": "pattern"
      },
      "regions": [
        {
          "start_line": 2602,
          "end_line": 2604
        }
      ]
    },
    {
      "patch_source": {
        "file": "smods-1.0.0-beta-1224a\\lovely\\scoring_calculation.toml",
        "pattern": "self.GAME.selected_back_key = selected_back\n",
        "patch_type": "pattern"
      },
      "regions": [
        {
          "start_line": 2086,
          "end_line": 2093
        }
      ]
    },
    {
      "patch_source": {
        "file": "smods-1.0.0-beta-1224a\\lovely\\shaders.toml",
        "pattern": "self.SHADERS[shader_name] = love.graphics.newShader(\"resources/shaders/\"..filename)",
        "patch_type": "pattern"
      },
      "regions": [
        {
          "start_line": 134,
          "end_line": 139
        }
      ]
    },
    {
      "patch_source": {
        "file": "smods-1.0.0-beta-1224a\\lovely\\shop.toml",
        "pattern": "for i = 1, 2 do\n    G.GAME.current_round.used_packs = G.GAME.current_round.used_packs or {}\n",
        "patch_type": "pattern"
      },
      "regions": [
        {
          "start_line": 3261,
          "end_line": 3262
        }
      ]
    },
    {
      "patch_source": {
        "file": "smods-1.0.0-beta-1224a\\lovely\\shop.toml",
        "pattern": "if G.GAME.current_round.voucher and G.P_CENTERS[G.GAME.current_round.voucher] then\n    local card = Card(G.shop_vouchers.T.x + G.shop_vouchers.T.w/2,\n    G.shop_vouchers.T.y, G.CARD_W, G.CARD_H, G.P_CARDS.empty, G.P_CENTERS[G.GAME.current_round.voucher],{bypass_discovery_center = true, bypass_discovery_ui = true})\n    card.shop_voucher = true\n    create_shop_card_ui(card, 'Voucher', G.shop_vouchers)\n    card:start_materialize()\n    G.shop_vouchers:emplace(card)\nend\n",
        "patch_type": "pattern"
      },
      "regions": [
        {
          "start_line": 3239,
          "end_line": 3248
        }
      ]
    },
    {
      "patch_source": {
        "file": "smods-1.0.0-beta-1224a\\lovely\\shop.toml",
        "pattern": "self.GAME.current_round.voucher = G.SETTINGS.tutorial_progress and G.SETTINGS.tutorial_progress.forced_voucher or get_next_voucher_key()\n",
        "patch_type": "pattern"
      },
      "regions": [
        {
          "start_line": 2245,
          "end_line": 2246
        }
      ]
    },
    {
      "patch_source": {
        "file": "smods-1.0.0-beta-1224a\\lovely\\shop.toml",
        "pattern": "reroll_cost = 1,\n",
        "patch_type": "pattern"
      },
      "regions": [
        {
          "start_line": 2006,
          "end_line": 2006
        }
      ]
    },
    {
      "patch_source": {
        "file": "smods-1.0.0-beta-1224a\\lovely\\stake.toml",
        "pattern": "if self.GAME.stake >= 2 then",
        "patch_type": "pattern"
      },
      "regions": [
        {
          "start_line": 2099,
          "end_line": 2099
        }
      ]
    },
    {
      "patch_source": {
        "file": "smods-1.0.0-beta-1224a\\lovely\\stake.toml",
        "pattern": "if self.GAME.stake >= 8 then self.GAME.modifiers.enable_rentals_in_shop = true end",
        "patch_type": "pattern"
      },
      "regions": [
        {
          "start_line": 2110,
          "end_line": 2110
        }
      ]
    },
    {
      "patch_source": {
        "file": "smods-1.0.0-beta-1224a\\lovely\\ui_additional_text_props.toml",
        "pattern": "v:update(dt*self.SPEEDFACTOR)\n",
        "patch_type": "pattern"
      },
      "regions": [
        {
          "start_line": 2742,
          "end_line": 2742
        }
      ]
    },
    {
      "patch_source": {
        "file": "smods-1.0.0-beta-1224a\\lovely\\booster.toml",
        "pattern": "(?<indent>[\\t ]*)if self\\.STATE == self\\.STATES\\.TAROT_PACK then",
        "patch_type": "regex"
      },
      "regions": [
        {
          "start_line": 2687,
          "end_line": 2690
        }
      ]
    },
    {
      "patch_source": {
        "file": "smods-1.0.0-beta-1224a\\lovely\\playing_card.toml",
        "pattern": "(?<indent>[\\t ]*)cards_played = \\{\\n(.*\\n){13}[\\t ]*\\},",
        "patch_type": "regex"
      },
      "regions": [
        {
          "start_line": 2024,
          "end_line": 2026
        }
      ]
    },
    {
      "patch_source": {
        "file": "smods-1.0.0-beta-1224a\\lovely\\seal.toml",
        "pattern": "(?<indent>[\\t ]*)Gold =[ {A-z=1-4,\"}\\n]*},[\\n\\t ]*}",
        "patch_type": "regex"
      },
      "regions": [
        {
          "start_line": 227,
          "end_line": 231
        }
      ]
    },
    {
      "patch_source": {
        "file": "smods-1.0.0-beta-1224a\\lovely\\challenge.toml",
        "pattern": "if _ch.restrictions.banned_cards then",
        "patch_type": "pattern"
      },
      "regions": [
        {
          "start_line": 2183,
          "end_line": 2185
        }
      ]
    },
    {
      "patch_source": {
        "file": "smods-1.0.0-beta-1224a\\lovely\\challenge.toml",
        "pattern": "if _ch.restrictions.banned_tags then",
        "patch_type": "pattern"
      },
      "regions": [
        {
          "start_line": 2196,
          "end_line": 2198
        }
      ]
    },
    {
      "patch_source": {
        "file": "smods-1.0.0-beta-1224a\\lovely\\challenge.toml",
        "pattern": "if _ch.restrictions.banned_other then",
        "patch_type": "pattern"
      },
      "regions": [
        {
          "start_line": 2204,
          "end_line": 2207
        }
      ]
    },
    {
      "patch_source": {
        "file": "smods-1.0.0-beta-1224a\\lovely\\challenge.toml",
        "pattern": "local _ch = args.challenge\n",
        "patch_type": "pattern"
      },
      "regions": [
        {
          "start_line": 2118,
          "end_line": 2120
        }
      ]
    },
    {
      "patch_source": {
        "file": "smods-1.0.0-beta-1224a\\lovely\\core.toml",
        "pattern": "self.SPEEDFACTOR = 1",
        "patch_type": "pattern"
      },
      "regions": [
        {
          "start_line": 215,
          "end_line": 215
        }
      ]
    },
    {
      "patch_source": {
        "file": "smods-1.0.0-beta-1224a\\lovely\\create_sprite.toml",
        "pattern": "        self.ANIMATION_ATLAS[self.animation_atli[i].name].frames = self.animation_atli[i].frames\n",
        "patch_type": "pattern"
      },
      "regions": [
        {
          "start_line": 1116,
          "end_line": 1116
        }
      ]
    },
    {
      "patch_source": {
        "file": "smods-1.0.0-beta-1224a\\lovely\\easings.toml",
        "pattern": "ease_value(card.T, 'scale', -card.T.scale, nil, nil, nil, 1.*speed, 'elastic')\n",
        "patch_type": "pattern"
      },
      "regions": [
        {
          "start_line": 1509,
          "end_line": 1509
        }
      ]
    },
    {
      "patch_source": {
        "file": "smods-1.0.0-beta-1224a\\lovely\\loader.toml",
        "pattern": "meta.alerted = meta.alerted or {}",
        "patch_type": "pattern"
      },
      "regions": [
        {
          "start_line": 753,
          "end_line": 763
        }
      ]
    },
    {
      "patch_source": {
        "file": "smods-1.0.0-beta-1224a\\lovely\\menu.toml",
        "pattern": "self.ASSET_ATLAS[self.asset_atli[i].name].image = love.graphics.newImage(self.asset_atli[i].path, {mipmaps = true, dpiscale = self.SETTINGS.GRAPHICS.texture_scaling})",
        "patch_type": "pattern"
      },
      "regions": [
        {
          "start_line": 1123,
          "end_line": 1126
        }
      ]
    },
    {
      "patch_source": {
        "file": "smods-1.0.0-beta-1224a\\lovely\\mod.toml",
        "pattern": "(?<indent>[\\t ]*)reset_castle_card\\(\\)",
        "patch_type": "regex"
      },
      "regions": [
        {
          "start_line": 2474,
          "end_line": 2479
        }
      ]
    },
    {
      "patch_source": {
        "file": "HandyBalatro\\lovely\\controls_insta_cash_out.toml",
        "pattern": "G.FUNCS.evaluate_round()",
        "patch_type": "pattern"
      },
      "regions": [
        {
          "start_line": 3459,
          "end_line": 3459
        }
      ]
    },
    {
      "patch_source": {
        "file": "HandyBalatro\\lovely\\controls_regular_keybinds.toml",
        "pattern": "if math.abs(G.shop.T.y - G.shop.VT.y) < 3 then",
        "patch_type": "pattern"
      },
      "regions": [
        {
          "start_line": 3204,
          "end_line": 3204
        }
      ]
    },
    {
      "patch_source": {
        "file": "HandyBalatro\\lovely\\controls_speed_multiplier.toml",
        "pattern": "self.SPEEDFACTOR = self.SPEEDFACTOR + math.max(0, math.abs(G.ACC) - 2)",
        "patch_type": "pattern"
      },
      "regions": [
        {
          "start_line": 2588,
          "end_line": 2591
        }
      ]
    },
    {
      "patch_source": {
        "file": "HandyBalatro\\lovely\\controls_speed_multiplier.toml",
        "pattern": "self.E_MANAGER:update(self.real_dt)",
        "patch_type": "pattern"
      },
      "regions": [
        {
          "start_line": 2611,
          "end_line": 2611
        }
      ]
    },
    {
      "patch_source": {
        "file": "HandyBalatro\\lovely\\ui.toml",
        "pattern": "self.GAME = saveTable and saveTable.GAME or self:init_game_object()",
        "patch_type": "pattern"
      },
      "regions": [
        {
          "start_line": 2069,
          "end_line": 2069
        }
      ]
    },
    {
      "patch_source": {
        "file": "HandyBalatro\\lovely\\controls_show_deck_preview.toml",
        "pattern": "G.CONTROLLER.held_buttons.triggerleft",
        "patch_type": "regex"
      },
      "regions": [
        {
          "start_line": 3124,
          "end_line": 3124
        },
        {
          "start_line": 3137,
          "end_line": 3137
        }
      ]
    },
    {
      "patch_source": {
        "file": "Talisman-main\\lovely.toml",
        "pattern": "replace_card.states.visible = false",
        "patch_type": "pattern"
      },
      "regions": [
        {
          "start_line": 1632,
          "end_line": 1632
        },
        {
          "start_line": 1814,
          "end_line": 1814
        }
      ]
    },
    {
      "patch_source": {
        "file": "Talisman-main\\lovely.toml",
        "pattern": "chips = 0,",
        "patch_type": "pattern"
      },
      "regions": [
        {
          "start_line": 1953,
          "end_line": 1953
        },
        {
          "start_line": 1973,
          "end_line": 1973
        }
      ]
    },
    {
      "patch_source": {
        "file": "Talisman-main\\lovely.toml",
        "pattern": "if G.GAME.chips - G.GAME.blind.chips >= 0 or G.GAME.current_round.hands_left < 1 then",
        "patch_type": "pattern"
      },
      "regions": [
        {
          "start_line": 3329,
          "end_line": 3329
        }
      ]
    },
    {
      "patch_source": {
        "file": "Talisman-main\\lovely.toml",
        "pattern": "ante = 1,",
        "patch_type": "pattern"
      },
      "regions": [
        {
          "start_line": 2010,
          "end_line": 2010
        }
      ]
    },
    {
      "patch_source": {
        "file": "Talisman-main\\lovely.toml",
        "pattern": "if new_game_obj then self.GAME = self:init_game_object() end",
        "patch_type": "pattern"
      },
      "regions": [
        {
          "start_line": 1273,
          "end_line": 1273
        }
      ]
    },
    {
      "patch_source": {
        "file": "Talisman-main\\lovely.toml",
        "pattern": "self.GAME = saveTable and saveTable.GAME or self:init_game_object()",
        "patch_type": "pattern"
      },
      "regions": [
        {
          "start_line": 2068,
          "end_line": 2068
        }
      ]
    },
    {
      "patch_source": {
        "file": "Talisman-main\\lovely.toml",
        "pattern": "function Game:update_hand_played(dt)",
        "patch_type": "pattern"
      },
      "regions": [
        {
          "start_line": 3319,
          "end_line": 3320
        }
      ]
    },
    {
      "patch_source": {
        "file": "Talisman-main\\lovely.toml",
        "pattern": "type = 'save_run',",
        "patch_type": "pattern"
      },
      "regions": [
        {
          "start_line": 2826,
          "end_line": 2826
        }
      ]
    },
    {
      "patch_source": {
        "file": "MobileLikeDragging\\lovely\\game.toml",
        "pattern": "(self.deck and self.deck.cards[1] and self.deck.cards[1].states.collide.is and ((not self.deck.cards[1].states.drag.is) or self.CONTROLLER.HID.touch) and (not self.CONTROLLER.HID.controller)) or ",
        "patch_type": "pattern"
      },
      "regions": [
        {
          "start_line": 3123,
          "end_line": 3123
        }
      ]
    },
    {
      "patch_source": {
        "file": "Galdur\\lovely.toml",
        "pattern": "local selected_back = saveTable and saveTable.BACK.name or (args.challenge and args.challenge.deck and args.challenge.deck.type) or (self.GAME.viewed_back and self.GAME.viewed_back.name) or self.GAME.selected_back and self.GAME.selected_back.name or 'Red Deck'",
        "patch_type": "pattern"
      },
      "regions": [
        {
          "start_line": 2065,
          "end_line": 2065
        }
      ]
    },
    {
      "patch_source": {
        "file": "CardSleeves-1.8.0\\lovely\\expected_to_match.toml",
        "pattern": "if not saveTable then\n    if args.seed then self.GAME.seeded = true end\n    self.GAME.pseudorandom.seed = args.seed or (not (G.SETTINGS.tutorial_complete or G.SETTINGS.tutorial_progress.completed_parts['big_blind']) and \"TUTORIAL\") or generate_starting_seed()\nend\n\nfor k, v in pairs(self.GAME.pseudorandom) do if v == 0 then self.GAME.pseudorandom[k] = pseudohash(k..self.GAME.pseudorandom.seed) end end\nself.GAME.pseudorandom.hashed_seed = pseudohash(self.GAME.pseudorandom.seed)\n",
        "patch_type": "pattern"
      },
      "regions": [
        {
          "start_line": 2226,
          "end_line": 2235
        }
      ]
    },
    {
      "patch_source": {
        "file": "CardSleeves-1.8.0\\lovely\\expected_to_match.toml",
        "pattern": "self.GAME.selected_back_key = selected_back",
        "patch_type": "pattern"
      },
      "regions": [
        {
          "start_line": 2079,
          "end_line": 2085
        }
      ]
    },
    {
      "patch_source": {
        "file": "CardSleeves-1.8.0\\lovely\\expected_to_match.toml",
        "pattern": "G.CONTROLLER:snap_to({node = G.shop:get_UIE_by_ID('next_round_button')})",
        "patch_type": "pattern"
      },
      "regions": [
        {
          "start_line": 3287,
          "end_line": 3300
        }
      ]
    },
    {
      "patch_source": {
        "file": "Blueprint-main\\lovely.toml",
        "pattern": "boot_timer('prep stage', 'splash prep',1)",
        "patch_type": "pattern"
      },
      "regions": [
        {
          "start_line": 218,
          "end_line": 218
        }
      ]
    },
    {
      "patch_source": {
        "file": "Blueprint-main\\lovely.toml",
        "pattern": "local shader_files = love.filesystem.getDirectoryItems(\"resources/shaders\")",
        "patch_type": "pattern"
      },
      "regions": [
        {
          "start_line": 128,
          "end_line": 128
        }
      ]
    }
  ]
}